LICENSE
README.md
setup.cfg
setup.py
eth_kms_signer/__init__.py
eth_kms_signer/client.py
eth_kms_signer/py.typed
eth_kms_signer/signer.py
eth_kms_signer.egg-info/PKG-INFO
eth_kms_signer.egg-info/SOURCES.txt
eth_kms_signer.egg-info/dependency_links.txt
eth_kms_signer.egg-info/not-zip-safe
eth_kms_signer.egg-info/requires.txt
eth_kms_signer.egg-info/top_level.txt
eth_kms_signer/utils/__init__.py
eth_kms_signer/utils/address.py
eth_kms_signer/utils/signing.py