Metadata-Version: 2.1
Name: eth-kms-signer
Version: 0.1.5
Summary: KMS signer for Ethereum
Home-page: https://github.com/viswanathkgp12/eth_kms_signer
Author: Viswanath Kapavarapu
Author-email: viswanath.iit@gmail.com
License: MIT
Platform: UNKNOWN
Classifier: Programming Language :: Python :: 3
Classifier: License :: OSI Approved :: MIT License
Classifier: Operating System :: OS Independent
Classifier: Intended Audience :: Developers
Requires-Python: >=3.5
License-File: LICENSE
